README.txt
setup.py
passk/__init__.py
passk/interface.py
passk/interfaceTxt.py
passk/passKeeper.py
passk.egg-info/PKG-INFO
passk.egg-info/SOURCES.txt
passk.egg-info/dependency_links.txt
passk.egg-info/requires.txt
passk.egg-info/top_level.txt