Metadata-Version: 1.2
Name: passk
Version: 1.6.4
Summary: Keeps things s.
Home-page: UNKNOWN
Author: APC
Author-email: apc.internet@pm.me
License: MIT
Platform: UNKNOWN
Requires-Python: >=3
